edc_python/__init__.py
edc_python/connector.py
edc_python/high_level_logic.py
edc_python/common/__init__.py
edc_python/common/id_generator.py
edc_python/common/util.py
edc_python/config/__init__.py
edc_python/config/config_parser.py
edc_python/config/connector_config.py
edc_python/rest_tools/__init__.py
edc_python/rest_tools/rest_connector.py
edc_python-0.3.0.dist-info/licenses/LICENSE
edc_python-0.3.0.dist-info/METADATA
edc_python-0.3.0.dist-info/WHEEL
edc_python-0.3.0.dist-info/top_level.txt
edc_python-0.3.0.dist-info/RECORD
