Metadata-Version: 2.4
Name: edc_python
Version: 0.3.0
Summary: Helps handling EDC Tractus X API with python.
Home-page: https://github.com/fluid40/edc_python
Author: Fluid 4.0
Author-email: "Fluid 4.0" <info@fluid40.de>
Maintainer-email: "Fluid 4.0" <info@fluid40.de>
License-Expression: MIT
Classifier: Development Status :: 4 - Beta
Classifier: Intended Audience :: Developers
Classifier: Programming Language :: Python :: 3.7
Classifier: Programming Language :: Python :: 3.8
Classifier: Programming Language :: Python :: 3.9
Classifier: Programming Language :: Python :: 3.10
Requires-Python: >=3.7
License-File: LICENSE
Requires-Dist: requests>=2.28.0
Requires-Dist: configargparse>=1.5.3
Dynamic: license-file
